falsecolor/__init__.py
falsecolor/coloring.py
falsecolor/dataobject.py
falsecolor/dataqueue.py
falsecolor/process.py
falsecolor/savethread.py
falsecolor-1.1.4.9.dist-info/LICENSE.txt
falsecolor-1.1.4.9.dist-info/METADATA
falsecolor-1.1.4.9.dist-info/WHEEL
falsecolor-1.1.4.9.dist-info/top_level.txt
falsecolor-1.1.4.9.dist-info/RECORD
